ragaai_catalyst/__init__.py
ragaai_catalyst/_version.py
ragaai_catalyst/dataset.py
ragaai_catalyst/evaluation.py
ragaai_catalyst/guard_executor.py
ragaai_catalyst/guardrails_manager.py
ragaai_catalyst/internal_api_completion.py
ragaai_catalyst/prompt_manager.py
ragaai_catalyst/proxy_call.py
ragaai_catalyst/ragaai_catalyst.py
ragaai_catalyst/redteaming_old.py
ragaai_catalyst/synthetic_data_generation.py
ragaai_catalyst/utils.py
ragaai_catalyst/redteaming/__init__.py
ragaai_catalyst/redteaming/evaluator.py
ragaai_catalyst/redteaming/llm_generator.py
ragaai_catalyst/redteaming/llm_generator_old.py
ragaai_catalyst/redteaming/red_teaming.py
ragaai_catalyst/redteaming/requirements.txt
ragaai_catalyst/redteaming/upload_result.py
ragaai_catalyst/redteaming/config/detectors.toml
ragaai_catalyst/redteaming/data_generator/scenario_generator.py
ragaai_catalyst/redteaming/data_generator/test_case_generator.py
ragaai_catalyst/redteaming/tests/grok.ipynb
ragaai_catalyst/redteaming/tests/stereotype.ipynb
ragaai_catalyst/redteaming/utils/issue_description.py
ragaai_catalyst/redteaming/utils/rt.png
ragaai_catalyst/tracers/__init__.py
ragaai_catalyst/tracers/distributed.py
ragaai_catalyst/tracers/tracer.py
ragaai_catalyst/tracers/agentic_tracing/README.md
ragaai_catalyst/tracers/agentic_tracing/__init__.py
ragaai_catalyst/tracers/agentic_tracing/data/__init__.py
ragaai_catalyst/tracers/agentic_tracing/data/data_structure.py
ragaai_catalyst/tracers/agentic_tracing/tracers/__init__.py
ragaai_catalyst/tracers/agentic_tracing/tracers/main_tracer.py
ragaai_catalyst/tracers/agentic_tracing/upload/__init__.py
ragaai_catalyst/tracers/agentic_tracing/upload/session_manager.py
ragaai_catalyst/tracers/agentic_tracing/upload/trace_uploader.py
ragaai_catalyst/tracers/agentic_tracing/upload/upload_agentic_traces.py
ragaai_catalyst/tracers/agentic_tracing/upload/upload_code.py
ragaai_catalyst/tracers/agentic_tracing/utils/__init__.py
ragaai_catalyst-2.2.5.6.dist-info/licenses/LICENSE
ragaai_catalyst-2.2.5.6.dist-info/METADATA
ragaai_catalyst-2.2.5.6.dist-info/WHEEL
ragaai_catalyst-2.2.5.6.dist-info/top_level.txt
ragaai_catalyst-2.2.5.6.dist-info/RECORD
