Metadata-Version: 2.4
Name: ragaai_catalyst
Version: 2.2.5.6
Summary: RAGA AI CATALYST
Author-email: Kiran Scaria <kiran.scaria@raga.ai>, Kedar Gaikwad <kedar.gaikwad@raga.ai>, Dushyant Mahajan <dushyant.mahajan@raga.ai>, Siddhartha Kosti <siddhartha.kosti@raga.ai>, Ritika Goel <ritika.goel@raga.ai>, Vijay Chaurasia <vijay.chaurasia@raga.ai>, Tushar Kumar <tushar.kumar@raga.ai>, Rishabh Pandey <rishabh.pandey@raga.ai>, Jyotsana C G <jyotsana@raga.ai>
Requires-Python: <=3.13.2,>=3.10
License-File: LICENSE
Requires-Dist: aiohttp>=3.10.2
Requires-Dist: langchain-core>=0.2.11
Requires-Dist: langchain>=0.2.11
Requires-Dist: openai>=1.57.0
Requires-Dist: pandas
Requires-Dist: groq>=0.11.0
Requires-Dist: pypdf>=5.3.1
Requires-Dist: google-genai>=1.3.0
Requires-Dist: Markdown>=3.7
Requires-Dist: litellm>=1.51.1
Requires-Dist: tenacity==8.3.0
Requires-Dist: tqdm>=4.66.5
Requires-Dist: llama-index>=0.10.0
Requires-Dist: pyopenssl>=24.2.1
Requires-Dist: psutil~=6.0.0
Requires-Dist: py-cpuinfo~=9.0.0
Requires-Dist: requests~=2.32.3
Requires-Dist: GPUtil~=1.4.0
Requires-Dist: ipynbname
Requires-Dist: tiktoken>=0.7.0
Requires-Dist: tomli>=2.0.0
Requires-Dist: rich>=13.9.4
Requires-Dist: openinference-instrumentation
Requires-Dist: openinference-instrumentation-llama-index
Requires-Dist: openinference-instrumentation-langchain
Requires-Dist: openinference-instrumentation-vertexai
Requires-Dist: openinference-instrumentation-anthropic
Requires-Dist: openinference-instrumentation-groq
Requires-Dist: openinference-instrumentation-litellm
Requires-Dist: openinference-instrumentation-mistralai
Requires-Dist: openinference-instrumentation-openai
Requires-Dist: openinference-instrumentation-bedrock
Requires-Dist: openinference-instrumentation-crewai
Requires-Dist: openinference-instrumentation-haystack
Requires-Dist: openinference-instrumentation-openai-agents
Requires-Dist: openinference-instrumentation-smolagents
Requires-Dist: openinference-instrumentation-google-adk
Requires-Dist: opentelemetry-sdk
Requires-Dist: opentelemetry-exporter-otlp
Requires-Dist: opentelemetry-proto>=1.12.0
Provides-Extra: dev
Requires-Dist: pytest>=8.3.5; extra == "dev"
Requires-Dist: pytest-cov; extra == "dev"
Requires-Dist: black; extra == "dev"
Requires-Dist: isort; extra == "dev"
Requires-Dist: mypy; extra == "dev"
Requires-Dist: flake8; extra == "dev"
Dynamic: license-file
